<instance version="4" description="" template="abilities">
	<group name="ability_bag">
		<enum name="activation" value="timed" comment="NOTE: 'TIMED' activation = the player has to press the button to activate, but does not specify a target.  &#xD;&#xA;&#xD;&#xA;Unlike a toggle, this cannot be turned off by the user - although eventually we will have activated abilities that can be cancelled by themselves." />
		<bool name="can_target_in_fow" value="False" />
		<float name="caster_close_in_distance" value="0" />
		<bool name="casters_can_evacuate" value="False" />
		<enum_table name="cost_to_player">
			<float name="action" value="0" />
			<float name="popcap" value="0" />
			<float name="command" value="0" />
			<float name="food" value="0" />
			<float name="wood" value="0" />
			<float name="stone" value="0" />
			<float name="gold" value="0" />
			<float name="militia_hre" value="0" />
		</enum_table>
		<string name="cursor_ghost_blueprint" value="" />
		<float name="cursor_ghost_blueprint_angle" value="0" />
		<bool name="disable_combat" value="False" />
		<bool name="disable_when_active" value="False" />
		<bool name="enable_in_building" value="False" />
		<bool name="enable_in_vehicle" value="False" />
		<bool name="engage_combat" value="False" />
		<float name="entity_busy_time" value="0" />
		<float name="facing_angle" value="5" />
		<bool name="facing_ignore" value="False" />
		<float name="final_close_in_distance" value="0" />
		<bool name="fire_and_forget" value="False" />
		<bool name="garrison_target" value="False" />
		<bool name="initial_recharge" value="False" />
		<bool name="move_back" value="False" />
		<float name="move_back_distance" value="10" />
		<float name="range" value="0.01" />
		<bool name="range_ignore" value="True" />
		<float name="recharge_time" value="0" comment="You will want to change this to match your intentions for the ability." />
		<bool name="refundable" value="True" />
		<bool name="require_no_shot_block" value="False" />
		<enum name="shared_timer" value="" />
		<bool name="shared_timer_player_wide" value="False" />
		<enum name="squad_caster" value="one_entity" comment="Determines who casts this ability and thus who is the target of the self/target actions.  For example in this ability if you had a squad with 5 entities in it, it would look like this:&#xD;&#xA;&#xD;&#xA;Squad is what we use in most cases.&#xD;&#xA;&#xD;&#xA;Entity is used only if you want to affect a specific entity or the ability is firing a weapon.&#xD;&#xA;&#xD;&#xA;All Entities is used if you want the entire squad to fire projectiles OR you need the ability to function/scale based on the number of units." />
		<enum name="target" value="tp_any" />
		<float name="toggled_recharge_time_off" value="0" />
		<float name="toggled_recharge_time_on" value="0" />
		<group name="ui_cursor">
			<string name="cursor_bad" value="" />
			<string name="cursor_good" value="" />
			<string name="cursor_nonmodal_good" value="" />
		</group>
		<group name="ui_info">
			<locstring name="extra_text" value="0" />
			<locstring name="help_text" value="67" mod="eca6173149134b76b78757235af2aa36" />
			<string name="hotkey_name" value="A" />
			<file name="icon_name" value="races\common\abilities\market_sell_food" />
			<string name="overlay_name" value="" />
			<bool name="reveal_for_decryption" value="False" />
			<locstring name="screen_name" value="66" mod="eca6173149134b76b78757235af2aa36" />
			<file name="icon_alternate_name" value="" />
			<locstring name="brief_text" value="0" />
			<locstring name="help_text_alternate" value="0" />
			<locstring name="screen_name_alternate" value="0" />
			<locstring name="screen_name_short" value="0" />
			<string name="debug_text" value="" />
			<string name="tooltip_data_template" value="FoodSellTooltipDataTemplate" />
			<enum name="ui_combine_type" value="union" />
			<template_reference name="brief_text_formatter" value="">
			</template_reference>
			<template_reference name="extra_text_formatter" value="">
			</template_reference>
			<template_reference name="help_text_formatter" value="">
			</template_reference>
			<template_reference name="help_text_alternate_formatter" value="">
			</template_reference>
			<template_reference name="screen_name_formatter" value="">
			</template_reference>
			<template_reference name="screen_name_alternate_formatter" value="">
			</template_reference>
			<template_reference name="screen_name_short_formatter" value="">
			</template_reference>
			<string name="sound" value="" />
			<string name="sound_alternative" value="" />
			<locstring name="help_text_controller" value="0" />
			<locstring name="extra_text_controller" value="0" />
		</group>
		<locstring name="ui_usage_txt" value="0" />
		<bool name="validate_actions" value="True" />
		<list name="requirements">
			<template_reference name="required" value="requirements\required_constructionstate" List.ItemID="1692116831">
				<enum name="reason" value="usage_and_display" />
				<locstring name="ui_name" value="0" />
				<bool name="do_construction_completion_check" value="True" />
			</template_reference>
			<template_reference name="required" value="requirements\required_statemodelbool" List.ItemID="1502927411">
				<locstring name="ui_name" value="0" />
				<enum name="reason" value="usage" />
				<enum name="key" value="imperial_age_wonder_constructed" />
				<enum name="data_source_type" value="player_datasource" />
				<bool name="default_value" value="True" />
				<bool name="compare_to_value" value="True" />
			</template_reference>
		</list>
		<enum name="ability_super" value="tp_none" />
		<bool name="ui_mini_map_capture" value="False" />
		<bool name="facing_ignore_during_active" value="False" />
		<instance_reference name="ui_range" value="" />
		<instance_reference name="ui_reticule" value="" />
		<float name="ui_reticule_radius_min" value="1" />
		<float name="ui_reticule_radius_max" value="1" />
		<enum name="pending_ability_out_of_range_behaviour" value="chase" />
		<enum name="ui_ability_group" value="group_primary" />
		<string name="ui_targetable_sm_key" value="" />
		<string name="ui_targetable_on_key" value="" />
		<string name="ui_targetable_off_key" value="" />
		<enum name="ui_targetable_receiver" value="local" />
		<enum name="ui_combine_type" value="intersection" />
		<enum_table name="ui_modal_highlight">
			<bool name="world_sector" value="False" />
			<bool name="map_sector" value="False" />
			<bool name="map_sector_hq_link_extender" value="False" />
		</enum_table>
		<enum name="ui_group_cast_type" value="single" />
		<list name="requirements_target">
		</list>
		<template_reference name="targeted_ability_option" value="options\none">
		</template_reference>
		<enum name="ui_direction_requirement" value="nondirectional" />
		<instance_reference name="cursor_ghost_ebp" value="" />
		<bool name="can_cast_whilst_constructing" value="False" />
		<list name="requirements_self_recharge">
		</list>
		<bool name="can_cast_outside_active_battle_field" value="False" />
		<enum_table name="cost_to_squad">
			<float name="action" value="0" />
			<float name="popcap" value="0" />
			<float name="command" value="0" />
			<float name="food" value="0" />
			<float name="wood" value="0" />
			<float name="stone" value="0" />
			<float name="gold" value="0" />
			<float name="militia_hre" value="0" />
		</enum_table>
		<bool name="ability_super_event_cue" value="False" />
		<enum name="ui_progress_bar_type" value="auto_bar" />
		<enum name="ui_ability_issue_type" value="Normal" />
		<string name="speech_code" value="" />
		<template_reference name="channeling" value="options\none">
		</template_reference>
		<bool name="can_be_interrupted" value="True" />
		<template_reference name="casting_option" value="options\none">
		</template_reference>
		<template_reference name="proxy_range_option" value="options\none">
		</template_reference>
		<instance_reference name="ability_category" value="" />
		<bool name="always_refund_cost_if_failed" value="False" />
		<instance_reference name="ui_menu" value="" />
		<int name="ui_combine_priority" value="0" />
		<enum name="statetree_ability_id" value="" />
		<instance_reference name="construction_preview_override" value="" />
		<group name="ui_position">
			<int name="ui_position_row" value="1" />
			<int name="ui_position_column" value="4" />
		</group>
		<bool name="construction_preview" value="False" />
		<state_tree_node name="entity_tree" value="" />
		<state_tree_node name="squad_tree" value="" />
		<float name="hold_period" value="0" />
		<state_tree_node name="statetree_node_prereq_self_requirement" value="" />
		<state_tree_node name="statetree_node_prereq_target_requirement" value="" />
		<state_tree_node name="statetree_node_prereq_self_recharge_requirement" value="" />
		<group name="ability_active_state_tree_group">
			<state_tree_node name="ability_activate_squad_tree" value="" />
			<state_tree_node name="ability_activate_entity_tree" value="" />
			<state_tree_node name="ability_activate_deferred_tree" value="" />
		</group>
		<bool name="clear_ability_on_blueprint_conversion" value="True" />
		<float name="min_range" value="0" />
		<instance_reference name="ability_description" value="" />
		<enum name="ability_description_storage_index" value="" />
		<int name="default_command_weight_modifier" value="0" />
		<state_tree_node name="global_tree" value="" />
		<bool name="ui_visibility_ignore_prerequisite" value="False" />
		<bool name="use_simbox_to_simbox_range" value="True" />
		<list name="ui_contextual_info">
		</list>
		<bool name="show_range_reticule_in_contruction_item_preview" value="False" />
		<bool name="ui_range_reticule_shows_while_active" value="False" />
		<bool name="can_move_to_cast" value="True" />
		<string name="toggle_ability_group" value="" />
		<bool name="ui_ability_can_display" value="True" />
		<instance_reference name="projectile_for_preview" value="" />
		<float name="can_use_ability_check_interval" value="0.125" />
		<bool name="should_trigger_immediately" value="False" />
		<list name="enable_in_unit_types">
		</list>
		<bool name="ui_range_reticule_can_cast_only" value="False" />
		<bool name="ui_range_reticule_first_caster_only" value="True" />
		<enum name="ui_target_origin_point" value="center" />
		<locstring name="ui_user_prompt_issue_message" value="0" />
		<bool name="ui_range_reticule_enable_team_color" value="False" />
		<bool name="can_passive_ability_create_formation_squad_group" value="False" />
		<bool name="can_cast_again_whilst_pending" value="True" />
		<list name="float_properties">
		</list>
		<list name="int_properties">
		</list>
		<bool name="can_queue_passive_ability" value="False" />
		<string name="ui_click_point_action_key" value="" />
		<bool name="ignore_teardown_on_convert" value="False" />
		<instance_reference name="hotkey_binding" value="hotkeys\hotkey_binding\building_market\sell_food" />
		<int name="default_command_additional_rally_weight_modifier" value="0" />
	</group>
	<uniqueid name="pbgid" value="1073741840" />
	<instance_reference name="parent_pbg" value="" />
</instance>