<instance version="4" description="" template="ebps">
	<list name="extensions">
		<template_reference name="exts" value="ebpextensions\entity_blueprint_ext" List.ItemID="-1885873905" List.ParentItemID="-1885873905">
			<bool name="browsable_in_editor" value="True" overrideParent="True" />
		</template_reference>
		<template_reference name="exts" value="ebpextensions\health_ext" List.ItemID="1919883890" List.ParentItemID="1919883890">
			<bool name="can_repair" value="True" overrideParent="True" />
			<float name="death_seconds" value="-1" overrideParent="True" />
			<bool name="delete_when_dead" value="False" overrideParent="True" />
		</template_reference>
		<template_reference name="exts" value="ebpextensions\site_ext" List.ItemID="722177752" List.ParentItemID="722177752">
			<bool name="snap_to_construction_grid" value="True" overrideParent="True" />
		</template_reference>
		<template_reference name="exts" value="ebpextensions\type_ext" List.ItemID="-1605745194" List.ParentItemID="-1605745194">
			<list name="race_type_list" overrideParent="True">
				<instance_reference name="race_type" value="racebps\hre" List.ItemID="1786824873" />
			</list>
		</template_reference>
		<template_reference name="exts" value="ebpextensions\construction_ext" List.ItemID="1682252342" List.ParentItemID="1682252342">
			<float name="orientation" value="0" overrideParent="True" />
			<bool name="construction_site_erase_inactive" value="False" overrideParent="True" />
		</template_reference>
		<template_reference name="exts" value="ebpextensions\ui_ext" List.ItemID="-962585606" List.ParentItemID="-962585606">
			<group name="ui_codex_info">
				<bool name="exclusive" value="True" overrideParent="True" />
			</group>
			<list name="ui_extra_infos" overrideParent="True">
				<template_reference name="ui_extra_info" value="info\ui_extra_info" List.ItemID="-2092971318">
					<file name="icon" value="influence_decorator" overrideParent="True" />
					<locstring name="description" value="0" />
					<template_reference name="description_formatter" value="ui_text_formatter" overrideParent="True">
						<list name="formatter_arguments">
							<int name="int_value" value="200" List.ItemID="-1687139164" />
						</list>
						<locstring name="formatter" value="11204532" />
					</template_reference>
				</template_reference>
			</list>
		</template_reference>
		<template_reference name="exts" value="ebpextensions\spawner_ext" List.ItemID="400767969" List.ParentItemID="400767969">
			<list name="spawn_items" overrideParent="True">
				<group name="spawn_item" comment="hussar - feudal age" List.ItemID="199615217">
					<instance_reference name="entity" value="" />
					<instance_reference name="squad" value="sbps\races\hre\unit_horseman_2_hre" overrideParent="True" />
					<bool name="spawn_at_map_entry_point" value="False" />
					<group name="ui_position">
						<int name="ui_position_row" value="1" />
						<int name="ui_position_column" value="1" />
					</group>
					<instance_reference name="ui_menu" value="" />
					<int name="number_to_spawn" value="1" />
					<enum_table name="item_cost_adjustment">
						<float name="action" value="0" />
						<float name="command" value="0" />
						<float name="popcap" value="0" />
						<float name="food" value="0" />
						<float name="wood" value="0" />
						<float name="stone" value="0" />
						<float name="gold" value="0" />
						<float name="militia_hre" value="0" />
					</enum_table>
					<locstring name="ui_screen_name" value="0" />
					<locstring name="ui_help_text" value="0" />
					<bool name="can_be_cancelled" value="True" />
					<int name="number_to_queue_up_to_when_modified" value="5" />
					<list name="additional_squads">
					</list>
					<instance_reference name="hotkey_binding" value="hotkeys\hotkey_binding\building_stable\produce_horseman" overrideParent="True" />
				</group>
				<group name="spawn_item" comment="hussar - castle age" List.ItemID="325397222">
					<instance_reference name="entity" value="" />
					<instance_reference name="squad" value="sbps\races\hre\unit_horseman_3_hre" overrideParent="True" />
					<bool name="spawn_at_map_entry_point" value="False" />
					<group name="ui_position">
						<int name="ui_position_row" value="1" />
						<int name="ui_position_column" value="1" />
					</group>
					<instance_reference name="ui_menu" value="" />
					<int name="number_to_spawn" value="1" />
					<enum_table name="item_cost_adjustment">
						<float name="action" value="0" />
						<float name="command" value="0" />
						<float name="popcap" value="0" />
						<float name="food" value="0" />
						<float name="wood" value="0" />
						<float name="stone" value="0" />
						<float name="gold" value="0" />
						<float name="militia_hre" value="0" />
					</enum_table>
					<locstring name="ui_screen_name" value="0" />
					<locstring name="ui_help_text" value="0" />
					<bool name="can_be_cancelled" value="True" />
					<int name="number_to_queue_up_to_when_modified" value="5" />
					<list name="additional_squads">
					</list>
					<instance_reference name="hotkey_binding" value="hotkeys\hotkey_binding\building_stable\produce_horseman" overrideParent="True" />
				</group>
				<group name="spawn_item" comment="hussar - imperial age" List.ItemID="-1329148327">
					<instance_reference name="entity" value="" />
					<instance_reference name="squad" value="sbps\races\hre\unit_horseman_4_hre" overrideParent="True" />
					<bool name="spawn_at_map_entry_point" value="False" />
					<group name="ui_position">
						<int name="ui_position_row" value="1" />
						<int name="ui_position_column" value="1" />
					</group>
					<instance_reference name="ui_menu" value="" />
					<int name="number_to_spawn" value="1" />
					<enum_table name="item_cost_adjustment">
						<float name="action" value="0" />
						<float name="command" value="0" />
						<float name="popcap" value="0" />
						<float name="food" value="0" />
						<float name="wood" value="0" />
						<float name="stone" value="0" />
						<float name="gold" value="0" />
						<float name="militia_hre" value="0" />
					</enum_table>
					<locstring name="ui_screen_name" value="0" />
					<locstring name="ui_help_text" value="0" />
					<bool name="can_be_cancelled" value="True" />
					<int name="number_to_queue_up_to_when_modified" value="5" />
					<list name="additional_squads">
					</list>
					<instance_reference name="hotkey_binding" value="hotkeys\hotkey_binding\building_stable\produce_horseman" overrideParent="True" />
				</group>
				<group name="spawn_item" comment="knight - castle age" List.ItemID="751401748">
					<instance_reference name="entity" value="" />
					<instance_reference name="squad" value="sbps\races\hre\unit_knight_3_hre" overrideParent="True" />
					<bool name="spawn_at_map_entry_point" value="False" />
					<group name="ui_position">
						<int name="ui_position_row" value="1" />
						<int name="ui_position_column" value="2" />
					</group>
					<instance_reference name="ui_menu" value="" />
					<int name="number_to_spawn" value="1" />
					<enum_table name="item_cost_adjustment">
						<float name="action" value="0" />
						<float name="command" value="0" />
						<float name="popcap" value="0" />
						<float name="food" value="0" />
						<float name="wood" value="0" />
						<float name="stone" value="0" />
						<float name="gold" value="0" />
						<float name="militia_hre" value="0" />
					</enum_table>
					<locstring name="ui_screen_name" value="0" />
					<locstring name="ui_help_text" value="0" />
					<bool name="can_be_cancelled" value="True" />
					<int name="number_to_queue_up_to_when_modified" value="5" />
					<list name="additional_squads">
					</list>
					<instance_reference name="hotkey_binding" value="hotkeys\hotkey_binding\building_stable\produce_knight" overrideParent="True" />
				</group>
				<group name="spawn_item" comment="knight - imperial age" List.ItemID="-1426575843">
					<instance_reference name="entity" value="" />
					<instance_reference name="squad" value="sbps\races\hre\unit_knight_4_hre" overrideParent="True" />
					<bool name="spawn_at_map_entry_point" value="False" />
					<group name="ui_position">
						<int name="ui_position_row" value="1" />
						<int name="ui_position_column" value="2" />
					</group>
					<instance_reference name="ui_menu" value="" />
					<int name="number_to_spawn" value="1" />
					<enum_table name="item_cost_adjustment">
						<float name="action" value="0" />
						<float name="command" value="0" />
						<float name="popcap" value="0" />
						<float name="food" value="0" />
						<float name="wood" value="0" />
						<float name="stone" value="0" />
						<float name="gold" value="0" />
						<float name="militia_hre" value="0" />
					</enum_table>
					<locstring name="ui_screen_name" value="0" />
					<locstring name="ui_help_text" value="0" />
					<bool name="can_be_cancelled" value="True" />
					<int name="number_to_queue_up_to_when_modified" value="5" />
					<list name="additional_squads">
					</list>
					<instance_reference name="hotkey_binding" value="hotkeys\hotkey_binding\building_stable\produce_knight" overrideParent="True" />
				</group>
				<group name="spawn_item" comment="Scout" List.ItemID="-1379361924">
					<instance_reference name="entity" value="" />
					<instance_reference name="squad" value="sbps\races\hre\unit_scout_1_hre" overrideParent="True" />
					<bool name="spawn_at_map_entry_point" value="False" />
					<group name="ui_position">
						<int name="ui_position_row" value="1" />
						<int name="ui_position_column" value="3" overrideParent="True" />
					</group>
					<instance_reference name="ui_menu" value="" />
					<int name="number_to_spawn" value="1" />
					<enum_table name="item_cost_adjustment">
						<float name="action" value="0" />
						<float name="command" value="0" />
						<float name="popcap" value="0" />
						<float name="food" value="0" />
						<float name="wood" value="0" />
						<float name="stone" value="0" />
						<float name="gold" value="0" />
						<float name="militia_hre" value="0" />
					</enum_table>
					<locstring name="ui_screen_name" value="0" />
					<locstring name="ui_help_text" value="0" />
					<bool name="can_be_cancelled" value="True" />
					<int name="number_to_queue_up_to_when_modified" value="5" />
					<list name="additional_squads">
					</list>
					<instance_reference name="hotkey_binding" value="hotkeys\hotkey_binding\building_stable\produce_scout" overrideParent="True" />
				</group>
			</list>
			<int name="max_queue_size_override" value="1000" overrideParent="True" />
		</template_reference>
		<template_reference name="exts" value="ebpextensions\ability_ext" List.ItemID="-589099880" List.ParentItemID="-589099880">
			<list name="abilities" overrideParent="True">
				<instance_reference name="ability" value="abilities\timed_abilities\civ_core\core_building_scuttle" List.ItemID="1458195862" />
				<instance_reference name="ability" value="abilities\timed_abilities\hre\influence_auto_repair_hre" List.ItemID="-330449431" />
			</list>
		</template_reference>
		<template_reference name="exts" value="ebpextensions\statemodel_ext" List.ItemID="1382659575" List.ParentItemID="1382659575">
			<instance_reference name="schema" value="statemodel_schema\buildings\civilizations\hre\unit_cavalry_hre" overrideParent="True" />
		</template_reference>
		<template_reference name="exts" value="ebpextensions\tier_ext" overrideParent="True" List.ItemID="1441853485" List.ListAction="Append">
			<list name="tier_group_list" overrideParent="True">
				<list name="tier_group" overrideParent="True" List.ItemID="-987902849">
					<group name="tier" List.ItemID="715403222">
						<list name="tier_requirements" overrideParent="True">
						</list>
						<instance_reference name="attachments" value="attachments\attachment_lists\civilizations\hre\buildings\unit_cavalry_hre\tier2_unit_cavalry_control_hre" />
						<template_reference name="statetree_tier_reached_actions" value="state_tree_reference_info">
							<state_tree_node name="ActionTree_OpeningBranch" value="" />
							<bool name="start_suspended" value="False" />
						</template_reference>
						<instance_reference name="statetree_tier_requirements_pbg" value="" />
						<instance_reference name="statetree_tier_pgb_upgrade_target_entity" value="" />
						<instance_reference name="statetree_tier_pgb_upgrade_target_squad" value="" />
						<string name="tier_attachment_action" value="" />
						<template_reference name="blueprint_conversion_parameters" value="blueprint_conversion_parameters">
							<bool name="reissue_commands" value="False" />
							<bool name="continue_state_trees" value="False" />
							<bool name="remove_from_pending_deaths" value="False" />
						</template_reference>
						<string name="inventory_category_to_refresh_on_tier_up" value="" />
					</group>
					<group name="tier" List.ItemID="-1987109599">
						<list name="tier_requirements">
							<template_reference name="requirement" value="requirements\required_player_upgrade" List.ItemID="540793011">
								<enum name="reason" value="usage" />
								<locstring name="ui_name" value="0" />
								<bool name="is_present" value="True" />
								<int name="max_completed" value="100" />
								<int name="min_completed" value="1" />
								<instance_reference name="upgrade_name" value="upgrade\dev\ages\castle_age" mod="eca6173149134b76b78757235af2aa36" />
								<bool name="include_queued" value="False" />
								<group name="include_pbg_parenting">
									<bool name="include_child_pbgs" value="False" />
									<bool name="include_parent_pbgs" value="False" />
								</group>
								<bool name="include_completed" value="True" />
							</template_reference>
						</list>
						<instance_reference name="attachments" value="attachments\attachment_lists\civilizations\hre\buildings\unit_cavalry_hre\tier3_unit_cavalry_control_hre" />
						<template_reference name="statetree_tier_reached_actions" value="state_tree_reference_info">
							<state_tree_node name="ActionTree_OpeningBranch" value="" />
							<bool name="start_suspended" value="False" />
						</template_reference>
						<instance_reference name="statetree_tier_requirements_pbg" value="upgrade\dev\ages\castle_age" mod="eca6173149134b76b78757235af2aa36" overrideParent="True" />
						<instance_reference name="statetree_tier_pgb_upgrade_target_entity" value="" />
						<instance_reference name="statetree_tier_pgb_upgrade_target_squad" value="" />
						<string name="tier_attachment_action" value="act_set_current_age_castle" overrideParent="True" />
						<template_reference name="blueprint_conversion_parameters" value="blueprint_conversion_parameters">
							<bool name="reissue_commands" value="False" />
							<bool name="continue_state_trees" value="False" />
							<bool name="remove_from_pending_deaths" value="False" />
						</template_reference>
						<string name="inventory_category_to_refresh_on_tier_up" value="" />
					</group>
					<group name="tier" List.ItemID="-1824532939">
						<list name="tier_requirements">
							<template_reference name="requirement" value="requirements\required_player_upgrade" List.ItemID="-1927069438">
								<enum name="reason" value="usage" />
								<locstring name="ui_name" value="0" />
								<bool name="is_present" value="True" />
								<int name="max_completed" value="100" />
								<int name="min_completed" value="1" />
								<instance_reference name="upgrade_name" value="upgrade\dev\ages\imperial_age" mod="eca6173149134b76b78757235af2aa36" />
								<bool name="include_queued" value="False" />
								<group name="include_pbg_parenting">
									<bool name="include_child_pbgs" value="False" />
									<bool name="include_parent_pbgs" value="False" />
								</group>
								<bool name="include_completed" value="True" />
							</template_reference>
						</list>
						<instance_reference name="attachments" value="attachments\attachment_lists\civilizations\hre\buildings\unit_cavalry_hre\tier4_unit_cavalry_control_hre" />
						<template_reference name="statetree_tier_reached_actions" value="state_tree_reference_info">
							<state_tree_node name="ActionTree_OpeningBranch" value="" />
							<bool name="start_suspended" value="False" />
						</template_reference>
						<instance_reference name="statetree_tier_requirements_pbg" value="upgrade\dev\ages\imperial_age" mod="eca6173149134b76b78757235af2aa36" overrideParent="True" />
						<instance_reference name="statetree_tier_pgb_upgrade_target_entity" value="" />
						<instance_reference name="statetree_tier_pgb_upgrade_target_squad" value="" />
						<string name="tier_attachment_action" value="act_set_current_age_imperial" overrideParent="True" />
						<template_reference name="blueprint_conversion_parameters" value="blueprint_conversion_parameters">
							<bool name="reissue_commands" value="False" />
							<bool name="continue_state_trees" value="False" />
							<bool name="remove_from_pending_deaths" value="False" />
						</template_reference>
						<string name="inventory_category_to_refresh_on_tier_up" value="" />
					</group>
				</list>
				<list name="tier_group" overrideParent="True" List.ItemID="-163336703">
					<group name="tier" List.ItemID="-1583423810">
						<list name="tier_requirements">
						</list>
						<instance_reference name="attachments" value="attachments\attachment_lists\civilizations\english\outskirts\military\military_01" overrideParent="True" />
						<template_reference name="statetree_tier_reached_actions" value="state_tree_reference_info">
							<state_tree_node name="ActionTree_OpeningBranch" value="" />
							<bool name="start_suspended" value="False" />
						</template_reference>
						<instance_reference name="statetree_tier_requirements_pbg" value="" />
						<instance_reference name="statetree_tier_pgb_upgrade_target_entity" value="" />
						<instance_reference name="statetree_tier_pgb_upgrade_target_squad" value="" />
						<string name="tier_attachment_action" value="" />
						<template_reference name="blueprint_conversion_parameters" value="blueprint_conversion_parameters">
							<bool name="reissue_commands" value="False" />
							<bool name="continue_state_trees" value="False" />
							<bool name="remove_from_pending_deaths" value="False" />
						</template_reference>
						<string name="inventory_category_to_refresh_on_tier_up" value="" />
					</group>
					<group name="tier" overrideParent="True" List.ItemID="-461874562">
						<list name="tier_requirements" overrideParent="True">
						</list>
						<instance_reference name="attachments" value="attachments\attachment_lists\civilizations\english\outskirts\military\military_02" overrideParent="True" />
						<template_reference name="statetree_tier_reached_actions" value="state_tree_reference_info">
							<state_tree_node name="ActionTree_OpeningBranch" value="" />
							<bool name="start_suspended" value="False" />
						</template_reference>
						<instance_reference name="statetree_tier_requirements_pbg" value="upgrade\dev\ages\feudal_age" overrideParent="True" />
						<instance_reference name="statetree_tier_pgb_upgrade_target_entity" value="" />
						<instance_reference name="statetree_tier_pgb_upgrade_target_squad" value="" />
						<string name="tier_attachment_action" value="" />
						<template_reference name="blueprint_conversion_parameters" value="blueprint_conversion_parameters">
							<bool name="reissue_commands" value="False" />
							<bool name="continue_state_trees" value="False" />
							<bool name="remove_from_pending_deaths" value="False" />
						</template_reference>
						<string name="inventory_category_to_refresh_on_tier_up" value="" />
					</group>
					<group name="tier" List.ItemID="258493694">
						<list name="tier_requirements" overrideParent="True">
						</list>
						<instance_reference name="attachments" value="attachments\attachment_lists\civilizations\english\outskirts\military\military_03" overrideParent="True" />
						<template_reference name="statetree_tier_reached_actions" value="state_tree_reference_info">
							<state_tree_node name="ActionTree_OpeningBranch" value="" />
							<bool name="start_suspended" value="False" />
						</template_reference>
						<instance_reference name="statetree_tier_requirements_pbg" value="upgrade\dev\ages\castle_age" mod="eca6173149134b76b78757235af2aa36" overrideParent="True" />
						<instance_reference name="statetree_tier_pgb_upgrade_target_entity" value="" />
						<instance_reference name="statetree_tier_pgb_upgrade_target_squad" value="" />
						<string name="tier_attachment_action" value="" />
						<template_reference name="blueprint_conversion_parameters" value="blueprint_conversion_parameters">
							<bool name="reissue_commands" value="False" />
							<bool name="continue_state_trees" value="False" />
							<bool name="remove_from_pending_deaths" value="False" />
						</template_reference>
						<string name="inventory_category_to_refresh_on_tier_up" value="" />
					</group>
					<group name="tier" List.ItemID="-397065672">
						<list name="tier_requirements" overrideParent="True">
						</list>
						<instance_reference name="attachments" value="attachments\attachment_lists\civilizations\english\outskirts\military\military_04" overrideParent="True" />
						<template_reference name="statetree_tier_reached_actions" value="state_tree_reference_info">
							<state_tree_node name="ActionTree_OpeningBranch" value="" />
							<bool name="start_suspended" value="False" />
						</template_reference>
						<instance_reference name="statetree_tier_requirements_pbg" value="upgrade\dev\ages\imperial_age" mod="eca6173149134b76b78757235af2aa36" overrideParent="True" />
						<instance_reference name="statetree_tier_pgb_upgrade_target_entity" value="" />
						<instance_reference name="statetree_tier_pgb_upgrade_target_squad" value="" />
						<string name="tier_attachment_action" value="" />
						<template_reference name="blueprint_conversion_parameters" value="blueprint_conversion_parameters">
							<bool name="reissue_commands" value="False" />
							<bool name="continue_state_trees" value="False" />
							<bool name="remove_from_pending_deaths" value="False" />
						</template_reference>
						<string name="inventory_category_to_refresh_on_tier_up" value="" />
					</group>
				</list>
			</list>
		</template_reference>
		<template_reference name="exts" value="ebpextensions\district_generator_ext" List.ItemID="-1661839879" List.ListAction="Append">
			<float name="range_metres" value="4" overrideParent="True" />
			<int name="generator_value" value="0" overrideParent="True" />
			<bool name="disable_generation_on_spawn" value="False" />
			<bool name="is_root_generator" value="False" />
			<int name="district_palette_id" value="0" />
		</template_reference>
		<template_reference name="exts" value="ebpextensions\district_bonuses_ext" List.ItemID="-172785863" List.ListAction="Append">
			<bool name="update_on_upgrade_changed" value="False" />
			<bool name="update_on_construction_complete" value="True" />
			<list name="district_bonuses" overrideParent="True">
				<template_reference name="district_bonus" value="district_bonus" comment="population" List.ItemID="-1013197504">
					<template_reference name="requirement" value="options\ebpextensions\districtbonusesext\requirements\district_bonus_entity_requirement">
						<list name="dynamic_requirements">
						</list>
						<list name="satisfying_entity_groups" overrideParent="True">
							<group name="satisfying_entity_group" comment="Town Center Capital&#xD;&#xA;" List.ItemID="-847928511">
								<list name="satisfying_entities">
									<instance_reference name="entity" value="ebps\races\hre\buildings\building_town_center_hre\building_town_center_capital_hre" mod="eca6173149134b76b78757235af2aa36" List.ItemID="-582545237" />
								</list>
							</group>
							<group name="satisfying_entity_group" comment="Town Center" List.ItemID="-736558879">
								<list name="satisfying_entities">
									<instance_reference name="entity" value="ebps\races\hre\buildings\building_town_center_hre\building_town_center_hre" List.ItemID="-419893493" />
								</list>
							</group>
							<group name="satisfying_entity_group" comment="Palace of Swabia" List.ItemID="1470434081">
								<list name="satisfying_entities">
									<instance_reference name="entity" value="ebps\races\hre\buildings\building_landmark_age3_hohenzollern_castle_hre\building_landmark_age3_hohenzollern_castle_hre" overrideParent="True" List.ItemID="-1751311977" />
								</list>
							</group>
						</list>
					</template_reference>
					<uniqueid name="id" value="1073741837" />
					<template_reference name="action_tree" value="state_tree_reference_info">
						<state_tree_node name="ActionTree_OpeningBranch" value="influence_auto_repair_hre\root" overrideParent="True" />
						<bool name="start_suspended" value="False" />
					</template_reference>
				</template_reference>
				<template_reference name="district_bonus" value="district_bonus" comment="Elzbach Palace Influence" List.ItemID="-1392011363">
					<template_reference name="requirement" value="options\ebpextensions\districtbonusesext\requirements\district_bonus_entity_requirement">
						<list name="dynamic_requirements">
						</list>
						<list name="satisfying_entity_groups" overrideParent="True">
							<group name="satisfying_entity_group" comment="Elzbach Palace&#xD;&#xA;" List.ItemID="-1452935295">
								<list name="satisfying_entities">
									<instance_reference name="entity" value="ebps\races\hre\buildings\building_landmark_age3_eltz_castle_hre\building_landmark_age3_eltz_castle_hre" overrideParent="True" List.ItemID="-352785895" />
								</list>
							</group>
						</list>
					</template_reference>
					<uniqueid name="id" value="1073741838" />
					<template_reference name="action_tree" value="state_tree_reference_info">
						<state_tree_node name="ActionTree_OpeningBranch" value="elzbach_palace_influence_bonus_hre\root" overrideParent="True" />
						<bool name="start_suspended" value="False" />
					</template_reference>
				</template_reference>
			</list>
		</template_reference>
	</list>
	<uniqueid name="pbgid" value="134871" />
	<instance_reference name="parent_pbg" value="ebps\races\core\buildings\building_unit_cavalry" />
</instance>